isoplex/__init__.py
isoplex/__main__.py
isoplex/cli.py
isoplex/isoplex.py
isoplex/utils.py
isoplex-0.1.0.dist-info/licenses/LICENSE
isoplex-0.1.0.dist-info/METADATA
isoplex-0.1.0.dist-info/WHEEL
isoplex-0.1.0.dist-info/entry_points.txt
isoplex-0.1.0.dist-info/top_level.txt
isoplex-0.1.0.dist-info/RECORD
