Metadata-Version: 2.4
Name: isoplex
Version: 0.1.0
Summary: Compute and filter isoforms or other features based on perplexity
Author: Fairlie Reese
Author-email: Fairlie Reese <fairlie.reese@gmail.com>
Maintainer-email: Fairlie Reese <fairlie.reese@gmail.com>
License: MIT
Project-URL: bugs, https://github.com/fairliereese/isoplex/issues
Project-URL: changelog, https://github.com/fairliereese/isoplex/blob/master/changelog.md
Project-URL: homepage, https://github.com/fairliereese/isoplex
Requires-Python: >=3.8
License-File: LICENSE
Requires-Dist: typer
Requires-Dist: pandas<3.0,>=2.2
Requires-Dist: numpy<2,>=1.26; python_version >= "3.12"
Requires-Dist: numpy<2,>=1.21; python_version < "3.12"
Provides-Extra: test
Requires-Dist: coverage; extra == "test"
Requires-Dist: pytest; extra == "test"
Requires-Dist: ruff; extra == "test"
Requires-Dist: ty; extra == "test"
Requires-Dist: ipdb; extra == "test"
Dynamic: license-file
